certbot_loopia.py
certbot_loopia-0.2.0.dist-info/DESCRIPTION.rst
certbot_loopia-0.2.0.dist-info/METADATA
certbot_loopia-0.2.0.dist-info/RECORD
certbot_loopia-0.2.0.dist-info/WHEEL
certbot_loopia-0.2.0.dist-info/entry_points.txt
certbot_loopia-0.2.0.dist-info/metadata.json
certbot_loopia-0.2.0.dist-info/top_level.txt
