Metadata-Version: 2.0
Name: certbot-loopia
Version: 0.2.0
Summary: Loopia DNS authentication plugin for Certbot
Home-page: https://www.github.com/runfalk/certbot-loopia
Author: Andreas Runfalk
Author-email: andreas@runfalk.se
License: BSD
Platform: UNKNOWN
Classifier: Development Status :: 2 - Pre-Alpha
Classifier: Environment :: Plugins
Classifier: Intended Audience :: Developers
Classifier: License :: OSI Approved :: BSD License
Classifier: Programming Language :: Python
Classifier: Programming Language :: Python :: 2.7
Classifier: Programming Language :: Python :: 3.3
Classifier: Programming Language :: Python :: 3.4
Classifier: Programming Language :: Python :: 3.5
Classifier: Programming Language :: Python :: 3.6
Classifier: Topic :: Internet :: Name Service (DNS)
Classifier: Topic :: System :: Systems Administration
Classifier: Topic :: Utilities
Requires-Dist: acme (>=0.17.0)
Requires-Dist: certbot (>=0.17.0)
Requires-Dist: loopialib (>=0.2.0)
Requires-Dist: zope.interface (>=4.4.0)
